biosonic/__init__.py
biosonic/compute/__init__.py
biosonic/compute/modulation.py
biosonic/compute/pitch.py
biosonic/compute/spectral.py
biosonic/compute/spectrotemporal.py
biosonic/compute/temporal.py
biosonic/compute/utils.py
biosonic/filter.py
biosonic/handle.py
biosonic/plot.py
biosonic/praat.py
biosonic/synthesize.py
biosonic-0.1.8.dist-info/METADATA
biosonic-0.1.8.dist-info/WHEEL
biosonic-0.1.8.dist-info/licenses/LICENSE.md
biosonic-0.1.8.dist-info/RECORD
