Metadata-Version: 2.4
Name: biosonic
Version: 0.1.8
Summary: The biosonic package contains tools for bioacoustic analysis.
License-Expression: BSD-3-Clause
License-File: LICENSE.md
Keywords: bioacoustics,signal,sound synthesis,biology,singal processing
Author: Lena Gies
Author-email: lena.gies@univie.ac.at
Maintainer: Lena Gies
Maintainer-email: lena.gies@univie.ac.at
Requires-Python: >=3.10
Classifier: Development Status :: 3 - Alpha
Classifier: Programming Language :: Python
Provides-Extra: plot
Provides-Extra: praat
Requires-Dist: matplotlib ; extra == "plot"
Requires-Dist: numpy (<2.4.0) ; python_version < "3.11"
Requires-Dist: numpy (>=2.4.0,<3.0) ; python_version >= "3.11"
Requires-Dist: pandas (>=2.3.3,<3.0.0)
Requires-Dist: praat-textgrids ; extra == "praat"
Requires-Dist: scipy (<1.16.3) ; python_version < "3.11"
Requires-Dist: scipy (>=1.16.3,<2.0.0) ; python_version >= "3.11"
Project-URL: Bug Tracker, https://github.com/lgies23/biosonic/issues
Project-URL: Documentation, https://biosonic.readthedocs.io
Project-URL: Homepage, https://github.com/lgies23/biosonic
Project-URL: Repository, https://github.com/lgies23/biosonic
